Metadata-Version: 2.4
Name: pypowerwall-server
Version: 0.1.10
Summary: A high-performance FastAPI-based server for monitoring and managing Tesla Powerwall systems
Author-email: Jason Cox <jason@jasonacox.com>
License-Expression: MIT
Project-URL: Homepage, https://github.com/jasonacox/pypowerwall-server
Project-URL: Repository, https://github.com/jasonacox/pypowerwall-server
Project-URL: Documentation, https://github.com/jasonacox/pypowerwall-server#readme
Project-URL: Bug Tracker, https://github.com/jasonacox/pypowerwall-server/issues
Keywords: tesla,powerwall,monitoring,api,fastapi
Classifier: Development Status :: 4 - Beta
Classifier: Intended Audience :: Developers
Classifier: Intended Audience :: End Users/Desktop
Classifier: Operating System :: OS Independent
Classifier: Programming Language :: Python :: 3
Classifier: Programming Language :: Python :: 3.10
Classifier: Programming Language :: Python :: 3.11
Classifier: Programming Language :: Python :: 3.12
Classifier: Topic :: Home Automation
Classifier: Topic :: System :: Monitoring
Requires-Python: >=3.10
License-File: LICENSE
Requires-Dist: fastapi>=0.115.0
Requires-Dist: uvicorn[standard]>=0.29.0
Requires-Dist: pydantic>=2.11.0
Requires-Dist: pydantic-settings>=2.9.0
Requires-Dist: pypowerwall>=0.14.0
Requires-Dist: aiohttp>=3.12.0
Requires-Dist: websockets>=13.1
Requires-Dist: psutil>=6.1.0
Requires-Dist: beautifulsoup4>=4.12.0
Dynamic: license-file
